kuva_metadata/__init__.py
kuva_metadata/custom_types.py
kuva_metadata/geometry_utils.py
kuva_metadata/helper_types.py
kuva_metadata/py.typed
kuva_metadata/sections_common.py
kuva_metadata/sections_l0.py
kuva_metadata/sections_l1.py
kuva_metadata/sections_l2.py
kuva_metadata/serializers.py
kuva_metadata/utils.py
kuva_metadata/validators.py
kuva_metadata-1.1.7.dist-info/METADATA
kuva_metadata-1.1.7.dist-info/WHEEL
kuva_metadata-1.1.7.dist-info/RECORD
