Metadata-Version: 2.4
Name: kuva-metadata
Version: 1.1.7
Summary: Definitions of Kuva Space product metadata
Author-email: Guillem Ballesteros <guillem@kuvaspace.com>, Lennert Antson <lennert.antson@kuvaspace.com>, Arthur Vandenhoeke <arthur.vandenhoeke@kuvaspace.com>, Olli Eloranta <olli.eloranta@kuvaspace.com>
License-Expression: MIT
Requires-Python: <=3.13,>=3.10
Requires-Dist: kuva-geometry<2.0.0,>=1.0.1
Requires-Dist: networkx<4.0.0,>=3.4.2
Requires-Dist: numpy-quaternion>=2022.4.4
Requires-Dist: numpy>=1.26.4
Requires-Dist: pint<1.0.0,>=0.22
Requires-Dist: pydantic<3.0.0,>=2.9.2
Requires-Dist: rasterio<2,>=1.4.3
Requires-Dist: shapely<3.0.0,>=2.0.6
Requires-Dist: sympy<2.0.0,>=1.13.3
